textotransformer/__init__.py
textotransformer/textotransformer.py
textotransformer/mensurador/__init__.py
textotransformer/mensurador/medidas.py
textotransformer/mensurador/mensurador.py
textotransformer/mensurador/mensuradorenum.py
textotransformer/modelo/__init__.py
textotransformer/modelo/modeloargumentos.py
textotransformer/modelo/modeloenum.py
textotransformer/modelo/transformer.py
textotransformer/modelo/transformeralbert.py
textotransformer/modelo/transformerbert.py
textotransformer/modelo/transformerdistilbert.py
textotransformer/modelo/transformerfactory.py
textotransformer/modelo/transformergpt2.py
textotransformer/modelo/transformeropenaigpt.py
textotransformer/modelo/transformerroberta.py
textotransformer/modelo/transformert5.py
textotransformer/modelo/transformerxlmroberta.py
textotransformer/modelo/transformerxlnet.py
textotransformer/modificador/__init__.py
textotransformer/modificador/modificador.py
textotransformer/pln/__init__.py
textotransformer/pln/pln.py
textotransformer/util/__init__.py
textotransformer/util/utilambiente.py
textotransformer/util/utilarquivo.py
textotransformer/util/utilconstantes.py
textotransformer/util/utiltempo.py
textotransformer/util/utiltexto.py
texto_transformer-0.0.12.dist-info/METADATA
texto_transformer-0.0.12.dist-info/WHEEL
texto_transformer-0.0.12.dist-info/licenses/LICENSE
texto_transformer-0.0.12.dist-info/RECORD
