Metadata-Version: 2.1
Name: texto-transformer
Version: 0.0.12
Summary: Texto Transformer: Framework para processamento de textos utilizando modelos de linguagem baseados baseados em Transformer
Project-URL: repository, https://github.com/osmarbraz/texto-transformer/
Author-email: Osmar de Oliveira Braz Junior <osmar.braz@udesc.br>
License: MIT License
License-File: LICENSE
Keywords: Framework,Transformer,embedding,palavra,sentença,texto,token
Classifier: Development Status :: 5 - Production/Stable
Classifier: Intended Audience :: Science/Research
Classifier: License :: OSI Approved :: MIT License
Classifier: Programming Language :: Python :: 3.9
Classifier: Topic :: Scientific/Engineering :: Artificial Intelligence
Requires-Python: >=3.9.0
Requires-Dist: numpy==1.22.4
Requires-Dist: protobuf==3.20.3
Requires-Dist: scipy==1.10.1
Requires-Dist: sentencepiece==0.1.99
Requires-Dist: spacy==3.5.2
Requires-Dist: torch==2.0.1
Requires-Dist: tqdm==4.65.0
Requires-Dist: transformers==4.26.1
